data_file_utils/__init__.py
data_file_utils/analyze_record_tuples.py
data_file_utils/archive_dir.py
data_file_utils/backup_dir.py
data_file_utils/backup_file.py
data_file_utils/compare_tab_files.py
data_file_utils/console_helper.py
data_file_utils/create_tmp_dir.py
data_file_utils/csv2tsv.py
data_file_utils/delete_users_files.py
data_file_utils/file_utils.py
data_file_utils/find_last_directory.py
data_file_utils/find_last_file.py
data_file_utils/jsonl2json.py
data_file_utils/profile_data_file.py
data_file_utils/tsv2json.py
data_file_utils/xlsx2tsv.py
data_file_utils/conf/config.yaml
data_file_utils-0.9.0.dist-info/AUTHORS.rst
data_file_utils-0.9.0.dist-info/LICENSE
data_file_utils-0.9.0.dist-info/METADATA
data_file_utils-0.9.0.dist-info/WHEEL
data_file_utils-0.9.0.dist-info/entry_points.txt
data_file_utils-0.9.0.dist-info/top_level.txt
data_file_utils-0.9.0.dist-info/RECORD
