Metadata-Version: 2.1
Name: data-file-utils
Version: 0.9.0
Summary: Collection of Python scripts/utils for file manipulation tasks
Home-page: https://github.com/jai-python3/data-file-utils
Author: Jaideep Sundaram
Author-email: jai.python3@gmail.com
Keywords: data_file_utils
Classifier: Development Status :: 2 - Pre-Alpha
Classifier: Intended Audience :: Developers
Classifier: Natural Language :: English
Classifier: Programming Language :: Python :: 3
Classifier: Programming Language :: Python :: 3.6
Classifier: Programming Language :: Python :: 3.7
Classifier: Programming Language :: Python :: 3.8
Requires-Python: >=3.6
License-File: LICENSE
License-File: AUTHORS.rst
Requires-Dist: Click >=7.0
Requires-Dist: PyYAML
Requires-Dist: Rich
Requires-Dist: pandas
Requires-Dist: xlsxwriter
